trustvault_sdk/__init__.py
trustvault_sdk/decorator.py
trustvault_sdk/logger.py
trustvault_sdk/tracer.py
trustvault_sdk-0.1.0.dist-info/licenses/LICENSE
trustvault_sdk-0.1.0.dist-info/METADATA
trustvault_sdk-0.1.0.dist-info/WHEEL
trustvault_sdk-0.1.0.dist-info/top_level.txt
trustvault_sdk-0.1.0.dist-info/RECORD
